talkie/__init__.py
talkie/__main__.py
talkie/cli/__init__.py
talkie/cli/main.py
talkie/cli/output.py
talkie/core/__init__.py
talkie/core/async_client.py
talkie/core/client.py
talkie/core/request_builder.py
talkie/core/response_formatter.py
talkie/core/websocket_client.py
talkie/utils/__init__.py
talkie/utils/benchmarks.py
talkie/utils/cache.py
talkie/utils/colors.py
talkie/utils/config.py
talkie/utils/curl_generator.py
talkie/utils/error_handler.py
talkie/utils/formatter.py
talkie/utils/graphql.py
talkie/utils/history.py
talkie/utils/logger.py
talkie/utils/memory_manager.py
talkie/utils/openapi.py
talkie/utils/openapi_generator.py
talkie/utils/performance_config.py
talkie/utils/validators.py
talkie-0.1.3.dist-info/METADATA
talkie-0.1.3.dist-info/WHEEL
talkie-0.1.3.dist-info/entry_points.txt
talkie-0.1.3.dist-info/licenses/LICENSE
talkie-0.1.3.dist-info/RECORD
