Metadata-Version: 2.4
Name: talkie
Version: 0.1.3
Summary: A command line HTTP client that is easy to use
Project-URL: Homepage, https://github.com/craxti/talkie
Project-URL: Documentation, https://github.com/craxti/talkie#readme
Project-URL: Repository, https://github.com/craxti/talkie
Project-URL: Bug Tracker, https://github.com/craxti/talkie/issues
Author: Craxti
License: MIT
License-File: LICENSE
Keywords: api,cli,curl,graphql,http,httpie,rest,websocket
Classifier: Development Status :: 4 - Beta
Classifier: Environment :: Console
Classifier: Intended Audience :: Developers
Classifier: License :: OSI Approved :: MIT License
Classifier: Programming Language :: Python :: 3
Classifier: Programming Language :: Python :: 3.8
Classifier: Programming Language :: Python :: 3.9
Classifier: Programming Language :: Python :: 3.10
Classifier: Programming Language :: Python :: 3.11
Classifier: Topic :: Internet :: WWW/HTTP
Classifier: Topic :: Software Development :: Libraries :: Python Modules
Classifier: Topic :: Utilities
Requires-Python: >=3.8
Requires-Dist: html2text>=2020.1.16
Requires-Dist: httpx>=0.24.0
Requires-Dist: openapi-spec-validator>=0.5.1
Requires-Dist: pydantic>=2.0.0
Requires-Dist: pygments>=2.14.0
Requires-Dist: pyyaml>=6.0
Requires-Dist: rich>=13.4.2
Requires-Dist: typer>=0.9.0
Requires-Dist: websockets>=10.4
Requires-Dist: xmltodict>=0.13.0
Provides-Extra: dev
Requires-Dist: black>=23.3.0; extra == 'dev'
Requires-Dist: flake8>=6.0.0; extra == 'dev'
Requires-Dist: isort>=5.12.0; extra == 'dev'
Requires-Dist: mkdocs-material>=9.0.0; extra == 'dev'
Requires-Dist: mkdocs>=1.5.0; extra == 'dev'
Requires-Dist: mypy>=1.3.0; extra == 'dev'
Requires-Dist: pillow>=10.0.0; extra == 'dev'
Requires-Dist: pre-commit>=3.0.0; extra == 'dev'
Requires-Dist: pylint>=3.0.0; extra == 'dev'
Requires-Dist: pytest-asyncio>=0.21.0; extra == 'dev'
Requires-Dist: pytest-cov>=4.1.0; extra == 'dev'
Requires-Dist: pytest-httpserver>=1.0.6; extra == 'dev'
Requires-Dist: pytest>=7.0.0; extra == 'dev'
